{
    "res": [{
        "NetworkService": 0.0064,
        "CrBrowserMain": 0.0025,
        "ThreadPoolForegroundWorker": 0,
        "Chrome_DevToolsHandlerThread": 0.0008,
        "Chrome_IOThread": 0.0009,
        "CacheThread_BlockFile": 0.0074,
        "StackSamplingProfiler": 0.0015,
        "ThreadPoolServiceThread": 0,
        "CompositorTileWorker1": 0.0006,
        "Chrome_ChildIOThread": 0.0004,
        "CrGpuMain": 0,
        "VizCompositorThread": 0.0016,
        "CrRendererMain": 0.0414,
        "Compositor": 0.0025,
        "CompositorTileWorker3": 0.0003,
        "CompositorTileWorker4": 0.0004,
        "CompositorTileWorker2": 0.0005,
        "": 0
    }, {
        "NetworkService": 0.0075,
        "CrBrowserMain": 0.0026,
        "ThreadPoolForegroundWorker": 0.0056,
        "Chrome_DevToolsHandlerThread": 0.0007,
        "Chrome_IOThread": 0.0013,
        "CacheThread_BlockFile": 0.006,
        "StackSamplingProfiler": 0.0007,
        "ThreadPoolServiceThread": 0,
        "CompositorTileWorker1": 0.0007,
        "Chrome_ChildIOThread": 0.0004,
        "CrGpuMain": 0.0002,
        "VizCompositorThread": 0.0025,
        "CrRendererMain": 0.3338,
        "Compositor": 0.0037,
        "CompositorTileWorker3": 0.0008,
        "CompositorTileWorker4": 0.0012,
        "CompositorTileWorker2": 0.0008,
        "ThreadPoolSingleThreadSharedForegroundBlocking0": 0,
        "ServiceWorker thread": 0.0036,
        "ThreadPoolSingleThreadSharedForeground1": 0,
        "": 0
    }, {
        "NetworkService": 0.0003,
        "CrBrowserMain": 0.0002,
        "ThreadPoolForegroundWorker": 0.0002,
        "Chrome_DevToolsHandlerThread": 0,
        "Chrome_IOThread": 0.0001,
        "CacheThread_BlockFile": 0.0003,
        "StackSamplingProfiler": 0.0001,
        "ThreadPoolServiceThread": 0,
        "CompositorTileWorker1": 0.0001,
        "Chrome_ChildIOThread": 0,
        "CrGpuMain": 0,
        "VizCompositorThread": 0.0001,
        "CrRendererMain": 0.0062,
        "Compositor": 0.0003,
        "CompositorTileWorker3": 0.0001,
        "CompositorTileWorker4": 0.0001,
        "CompositorTileWorker2": 0.0001,
        "": 0
    }, {
        "ThreadPoolForegroundWorker": 0.0003,
        "Chrome_ChildIOThread": 0.0006,
        "CrGpuMain": 0,
        "VizCompositorThread": 0.002,
        "NetworkService": 0.008,
        "CrBrowserMain": 0.0033,
        "Chrome_DevToolsHandlerThread": 0.0012,
        "Chrome_IOThread": 0.0008,
        "CacheThread_BlockFile": 0.0028,
        "StackSamplingProfiler": 0.0003,
        "ThreadPoolServiceThread": 0,
        "CompositorTileWorker1": 0.0007,
        "CrRendererMain": 0.0382,
        "Compositor": 0.0029,
        "CompositorTileWorker2": 0.0007,
        "CompositorTileWorker4": 0.0008,
        "CompositorTileWorker3": 0.0007,
        "DedicatedWorker thread": 0.0003,
        "": 0
    }, {
        "NetworkService": 0.0035,
        "CrBrowserMain": 0.0007,
        "ThreadPoolForegroundWorker": 0.0001,
        "Chrome_DevToolsHandlerThread": 0.0004,
        "Chrome_IOThread": 0.0002,
        "CacheThread_BlockFile": 0.0018,
        "StackSamplingProfiler": 0,
        "CompositorTileWorker1": 0.0003,
        "ThreadPoolServiceThread": 0,
        "Chrome_ChildIOThread": 0.0002,
        "CrGpuMain": 0,
        "VizCompositorThread": 0.0001,
        "CrRendererMain": 0.0061,
        "Compositor": 0.0002,
        "CompositorTileWorker3": 0.0002,
        "CompositorTileWorker4": 0.0001,
        "CompositorTileWorker2": 0.0002,
        "": 0
    }, {
        "NetworkService": 0.0038,
        "CrBrowserMain": 0.0011,
        "ThreadPoolForegroundWorker": 0,
        "Chrome_DevToolsHandlerThread": 0.0005,
        "Chrome_IOThread": 0.0004,
        "CacheThread_BlockFile": 0.002,
        "StackSamplingProfiler": 0.0001,
        "ThreadPoolServiceThread": 0,
        "CompositorTileWorker1": 0.0002,
        "CrRendererMain": 0.0246,
        "Chrome_ChildIOThread": 0,
        "Compositor": 0.0014,
        "CompositorTileWorker3": 0.0003,
        "CompositorTileWorker4": 0.0002,
        "CompositorTileWorker2": 0.0002,
        "CompositorTileWorkerBackground": 0.0002,
        "": 0,
        "CrGpuMain": 0.0001,
        "VizCompositorThread": 0.0012
    }, {
        "CrRendererMain": 0.0221,
        "ThreadPoolForegroundWorker": 0,
        "Chrome_ChildIOThread": 0,
        "Compositor": 0.0009,
        "ThreadPoolSingleThreadSharedForeground1": 0,
        "CompositorTileWorker2": 0.0002,
        "CompositorTileWorker4": 0.0001,
        "CompositorTileWorker1": 0,
        "CompositorTileWorker3": 0.0001,
        "DedicatedWorker thread": 0.0006,
        "": 0,
        "NetworkService": 0.0024,
        "CrBrowserMain": 0.001,
        "Chrome_DevToolsHandlerThread": 0.0003,
        "Chrome_IOThread": 0.0003,
        "CacheThread_BlockFile": 0.0021,
        "StackSamplingProfiler": 0.0002,
        "ThreadPoolServiceThread": 0,
        "CrGpuMain": 0,
        "VizCompositorThread": 0.0005
    }, {
        "NetworkService": 0.0071,
        "CrBrowserMain": 0.0032,
        "ThreadPoolForegroundWorker": 0.0001,
        "Chrome_DevToolsHandlerThread": 0.001,
        "Chrome_IOThread": 0.001,
        "CacheThread_BlockFile": 0.0055,
        "StackSamplingProfiler": 0,
        "CompositorTileWorker1": 0.0001,
        "ThreadPoolServiceThread": 0,
        "Chrome_ChildIOThread": 0.0007,
        "CrGpuMain": 0,
        "VizCompositorThread": 0.0004,
        "CrRendererMain": 0.0267,
        "Compositor": 0.0006,
        "CompositorTileWorker3": 0.0001,
        "CompositorTileWorker4": 0.0001,
        "CompositorTileWorker2": 0.0001,
        "ThreadPoolSingleThreadSharedForeground1": 0,
        "": 0
    }, {
        "ThreadPoolForegroundWorker": 0,
        "Chrome_ChildIOThread": 0,
        "CrGpuMain": 0,
        "VizCompositorThread": 0,
        "CrRendererMain": 0.0007,
        "Compositor": 0,
        "CompositorTileWorker4": 0,
        "CompositorTileWorker1": 0,
        "Database thread": 0.0004,
        "CompositorTileWorker2": 0,
        "": 0,
        "NetworkService": 0.0001,
        "CrBrowserMain": 0.0001,
        "Chrome_DevToolsHandlerThread": 0,
        "Chrome_IOThread": 0,
        "CacheThread_BlockFile": 0.0001,
        "StackSamplingProfiler": 0,
        "ThreadPoolServiceThread": 0
    }, {
        "NetworkService": 0.0007,
        "CrBrowserMain": 0.0002,
        "ThreadPoolForegroundWorker": 0,
        "Chrome_DevToolsHandlerThread": 0.0001,
        "Chrome_IOThread": 0.0001,
        "CacheThread_BlockFile": 0.0004,
        "StackSamplingProfiler": 0,
        "ThreadPoolServiceThread": 0,
        "CompositorTileWorker1": 0.0002,
        "Chrome_ChildIOThread": 0,
        "CrGpuMain": 0,
        "VizCompositorThread": 0.0003,
        "CrRendererMain": 0.0066,
        "Compositor": 0.0005,
        "CompositorTileWorker3": 0.0001,
        "CompositorTileWorker4": 0.0001,
        "CompositorTileWorker2": 0.0002,
        "CompositorTileWorkerBackground": 0,
        "": 0
    }, {
        "CrRendererMain": 0.0008,
        "ThreadPoolForegroundWorker": 0,
        "Chrome_ChildIOThread": 0,
        "Compositor": 0,
        "CompositorTileWorker3": 0,
        "CompositorTileWorker4": 0,
        "CompositorTileWorker1": 0,
        "CompositorTileWorker2": 0,
        "ThreadPoolSingleThreadSharedForegroundBlocking0": 0,
        "Media": 0,
        "": 0,
        "NetworkService": 0.0002,
        "CrBrowserMain": 0.0001,
        "Chrome_DevToolsHandlerThread": 0,
        "Chrome_IOThread": 0,
        "CacheThread_BlockFile": 0.0001,
        "StackSamplingProfiler": 0,
        "ThreadPoolServiceThread": 0,
        "CrGpuMain": 0,
        "VizCompositorThread": 0
    }, {
        "NetworkService": 0.0003,
        "CrBrowserMain": 0.0001,
        "ThreadPoolForegroundWorker": 0,
        "Chrome_DevToolsHandlerThread": 0,
        "Chrome_IOThread": 0,
        "CacheThread_BlockFile": 0.0002,
        "StackSamplingProfiler": 0,
        "ThreadPoolServiceThread": 0,
        "CompositorTileWorker1": 0,
        "Chrome_ChildIOThread": 0,
        "CrGpuMain": 0,
        "VizCompositorThread": 0.0002,
        "CrRendererMain": 0.0014,
        "Compositor": 0.0002,
        "CompositorTileWorker3": 0,
        "CompositorTileWorker4": 0,
        "CompositorTileWorker2": 0,
        "": 0
    }, {
        "NetworkService": 0.0002,
        "CrBrowserMain": 0.0001,
        "ThreadPoolForegroundWorker": 0,
        "Chrome_DevToolsHandlerThread": 0,
        "Chrome_IOThread": 0,
        "CacheThread_BlockFile": 0.0002,
        "StackSamplingProfiler": 0,
        "ThreadPoolServiceThread": 0,
        "CompositorTileWorker1": 0,
        "Chrome_ChildIOThread": 0,
        "CrGpuMain": 0,
        "VizCompositorThread": 0,
        "CrRendererMain": 0.0013,
        "Compositor": 0,
        "CompositorTileWorker4": 0,
        "CompositorTileWorker3": 0,
        "CompositorTileWorker2": 0,
        "": 0
    }, {
        "CrRendererMain": 0.0012,
        "ThreadPoolForegroundWorker": 0,
        "Chrome_ChildIOThread": 0,
        "Compositor": 0.0001,
        "CompositorTileWorker2": 0,
        "CompositorTileWorker4": 0,
        "CompositorTileWorker1": 0,
        "CompositorTileWorker3": 0,
        "ThreadPoolSingleThreadSharedForegroundBlocking0": 0,
        "ServiceWorker thread": 0,
        "ThreadPoolSingleThreadSharedForeground1": 0,
        "": 0,
        "NetworkService": 0.0002,
        "CrBrowserMain": 0.0001,
        "Chrome_DevToolsHandlerThread": 0,
        "Chrome_IOThread": 0,
        "CacheThread_BlockFile": 0.0001,
        "StackSamplingProfiler": 0,
        "ThreadPoolServiceThread": 0,
        "CrGpuMain": 0,
        "VizCompositorThread": 0.0001
    }, {
        "ThreadPoolForegroundWorker": 0,
        "Chrome_ChildIOThread": 0,
        "CrGpuMain": 0.0001,
        "VizCompositorThread": 0,
        "NetworkService": 0.0001,
        "CrBrowserMain": 0.0001,
        "Chrome_DevToolsHandlerThread": 0,
        "Chrome_IOThread": 0,
        "CacheThread_BlockFile": 0.0001,
        "StackSamplingProfiler": 0,
        "ThreadPoolServiceThread": 0,
        "CompositorTileWorker1": 0,
        "CrRendererMain": 0.001,
        "Compositor": 0.0001,
        "ThreadPoolSingleThreadSharedForegroundBlocking0": 0,
        "ServiceWorker thread": 0.0001,
        "CompositorTileWorker2": 0,
        "CompositorTileWorker4": 0,
        "CompositorTileWorker3": 0,
        "": 0
    }, {
        "NetworkService": 0.0011,
        "CrBrowserMain": 0.0004,
        "ThreadPoolForegroundWorker": 0,
        "Chrome_DevToolsHandlerThread": 0.0002,
        "Chrome_IOThread": 0.0001,
        "CacheThread_BlockFile": 0.0006,
        "StackSamplingProfiler": 0,
        "CompositorTileWorker1": 0,
        "ThreadPoolServiceThread": 0,
        "CrRendererMain": 0.0048,
        "Chrome_ChildIOThread": 0,
        "Compositor": 0.0002,
        "CompositorTileWorker2": 0,
        "CompositorTileWorker4": 0,
        "CompositorTileWorker3": 0,
        "ThreadPoolSingleThreadSharedForegroundBlocking0": 0,
        "Media": 0,
        "": 0,
        "CrGpuMain": 0,
        "VizCompositorThread": 0.0002
    }, {
        "NetworkService": 0,
        "CrBrowserMain": 0,
        "ThreadPoolForegroundWorker": 0,
        "Chrome_DevToolsHandlerThread": 0,
        "Chrome_IOThread": 0,
        "CacheThread_BlockFile": 0,
        "StackSamplingProfiler": 0,
        "ThreadPoolSingleThreadForegroundBlocking1": 0,
        "CompositorTileWorker1": 0,
        "MemoryInfra": 0,
        "Chrome_ChildIOThread": 0,
        "CrGpuMain": 0,
        "VizCompositorThread": 0,
        "CrRendererMain": 0,
        "Compositor": 0,
        "CompositorTileWorker3": 0,
        "GpuMemoryThread": 0,
        "ThreadPoolServiceThread": 0,
        "CompositorTileWorker2": 0,
        "": 0
    }, {
        "NetworkService": 0.0006,
        "CrBrowserMain": 0.0002,
        "ThreadPoolForegroundWorker": 0,
        "Chrome_DevToolsHandlerThread": 0.0001,
        "Chrome_IOThread": 0.0001,
        "CacheThread_BlockFile": 0.0003,
        "StackSamplingProfiler": 0,
        "ThreadPoolServiceThread": 0,
        "CompositorTileWorker1": 0,
        "Chrome_ChildIOThread": 0,
        "CrGpuMain": 0,
        "VizCompositorThread": 0,
        "CrRendererMain": 0.0031,
        "Compositor": 0.0001,
        "CompositorTileWorker3": 0.0001,
        "CompositorTileWorker4": 0,
        "CompositorTileWorker2": 0,
        "ThreadPoolSingleThreadSharedForeground1": 0,
        "": 0
    }, {
        "NetworkService": 0,
        "CrBrowserMain": 0,
        "ThreadPoolForegroundWorker": 0,
        "Chrome_DevToolsHandlerThread": 0,
        "Chrome_IOThread": 0,
        "CacheThread_BlockFile": 0,
        "StackSamplingProfiler": 0,
        "ThreadPoolServiceThread": 0,
        "ThreadPoolSingleThreadForegroundBlocking1": 0,
        "CompositorTileWorker1": 0,
        "MemoryInfra": 0,
        "CrRendererMain": 0,
        "Chrome_ChildIOThread": 0,
        "Compositor": 0,
        "CompositorTileWorker3": 0,
        "CrGpuMain": 0,
        "VizCompositorThread": 0,
        "GpuMemoryThread": 0,
        "CompositorTileWorker2": 0,
        "": 0
    }, {
        "ThreadPoolForegroundWorker": 0,
        "CrRendererMain": 0.0115,
        "Chrome_ChildIOThread": 0,
        "Compositor": 0.0003,
        "CompositorTileWorker3": 0,
        "CompositorTileWorker4": 0,
        "CompositorTileWorker1": 0,
        "CompositorTileWorker2": 0,
        "ThreadPoolSingleThreadSharedForegroundBlocking0": 0,
        "ServiceWorker thread": 0.0002,
        "ThreadPoolSingleThreadSharedForeground1": 0,
        "WebRTC_Worker": 0,
        "WebRTC_Signaling": 0,
        "ThreadPoolServiceThread": 0,
        "": 0,
        "NetworkService": 0.0013,
        "CrBrowserMain": 0.0005,
        "Chrome_DevToolsHandlerThread": 0.0001,
        "Chrome_IOThread": 0.0002,
        "CacheThread_BlockFile": 0.0005,
        "StackSamplingProfiler": 0,
        "CrGpuMain": 0,
        "VizCompositorThread": 0.0001
    }, {
        "NetworkService": 0,
        "CrBrowserMain": 0,
        "ThreadPoolForegroundWorker": 0,
        "Chrome_DevToolsHandlerThread": 0,
        "Chrome_IOThread": 0,
        "CacheThread_BlockFile": 0,
        "StackSamplingProfiler": 0,
        "ThreadPoolSingleThreadForegroundBlocking1": 0,
        "CompositorTileWorker1": 0,
        "MemoryInfra": 0,
        "Chrome_ChildIOThread": 0,
        "CrGpuMain": 0,
        "VizCompositorThread": 0,
        "CrRendererMain": 0,
        "Compositor": 0,
        "CompositorTileWorker2": 0,
        "ThreadPoolServiceThread": 0,
        "GpuMemoryThread": 0,
        "": 0
    }, {
        "NetworkService": 0.0001,
        "CrBrowserMain": 0,
        "ThreadPoolForegroundWorker": 0,
        "Chrome_DevToolsHandlerThread": 0,
        "Chrome_IOThread": 0,
        "CacheThread_BlockFile": 0.0001,
        "StackSamplingProfiler": 0,
        "ThreadPoolServiceThread": 0,
        "CompositorTileWorker1": 0,
        "CrRendererMain": 0.0006,
        "Chrome_ChildIOThread": 0,
        "Compositor": 0.0001,
        "CompositorTileWorker2": 0,
        "CompositorTileWorker4": 0,
        "CompositorTileWorker3": 0,
        "": 0,
        "CrGpuMain": 0,
        "VizCompositorThread": 0
    }, {
        "NetworkService": 0.0003,
        "CrBrowserMain": 0.0001,
        "ThreadPoolForegroundWorker": 0,
        "Chrome_DevToolsHandlerThread": 0,
        "Chrome_IOThread": 0,
        "CacheThread_BlockFile": 0.0003,
        "StackSamplingProfiler": 0,
        "ThreadPoolServiceThread": 0,
        "CompositorTileWorker1": 0,
        "ThreadPoolSingleThreadForegroundBlocking1": 0,
        "MemoryInfra": 0,
        "CrRendererMain": 0.0036,
        "Chrome_ChildIOThread": 0,
        "Compositor": 0.0002,
        "CompositorTileWorker3": 0,
        "CompositorTileWorker4": 0,
        "CompositorTileWorker2": 0,
        "OfflineAudioRender thread": 0,
        "": 0,
        "CrGpuMain": 0.0001,
        "VizCompositorThread": 0
    }, {
        "NetworkService": 0.0002,
        "CrBrowserMain": 0.0001,
        "ThreadPoolForegroundWorker": 0,
        "Chrome_DevToolsHandlerThread": 0,
        "Chrome_IOThread": 0,
        "CacheThread_BlockFile": 0.0001,
        "StackSamplingProfiler": 0,
        "CompositorTileWorker1": 0,
        "ThreadPoolServiceThread": 0,
        "ThreadPoolSingleThreadForegroundBlocking1": 0,
        "MemoryInfra": 0,
        "Chrome_ChildIOThread": 0,
        "CrGpuMain": 0,
        "VizCompositorThread": 0,
        "CrRendererMain": 0.0008,
        "Compositor": 0.0001,
        "CompositorTileWorker3": 0,
        "CompositorTileWorker4": 0,
        "CompositorTileWorker2": 0,
        "CompositorTileWorkerBackground": 0,
        "": 0
    }, {
        "CrRendererMain": 0.0005,
        "ThreadPoolForegroundWorker": 0,
        "Chrome_ChildIOThread": 0,
        "Compositor": 0,
        "CompositorTileWorker3": 0,
        "CompositorTileWorker4": 0,
        "CompositorTileWorker1": 0,
        "CompositorTileWorker2": 0,
        "": 0,
        "NetworkService": 0.0001,
        "CrBrowserMain": 0,
        "Chrome_DevToolsHandlerThread": 0,
        "Chrome_IOThread": 0,
        "CacheThread_BlockFile": 0.0001,
        "StackSamplingProfiler": 0,
        "ThreadPoolServiceThread": 0,
        "CrGpuMain": 0,
        "VizCompositorThread": 0
    }, {
        "NetworkService": 0.0002,
        "CrBrowserMain": 0,
        "ThreadPoolForegroundWorker": 0,
        "Chrome_DevToolsHandlerThread": 0,
        "Chrome_IOThread": 0,
        "CacheThread_BlockFile": 0.0001,
        "StackSamplingProfiler": 0,
        "CompositorTileWorker1": 0,
        "ThreadPoolServiceThread": 0,
        "Chrome_ChildIOThread": 0,
        "CrGpuMain": 0,
        "VizCompositorThread": 0,
        "CrRendererMain": 0.0007,
        "Compositor": 0,
        "CompositorTileWorker3": 0,
        "CompositorTileWorker4": 0,
        "CompositorTileWorker2": 0,
        "": 0
    }, {
        "NetworkService": 0.0001,
        "CrBrowserMain": 0,
        "ThreadPoolForegroundWorker": 0,
        "Chrome_DevToolsHandlerThread": 0,
        "Chrome_IOThread": 0,
        "CacheThread_BlockFile": 0,
        "StackSamplingProfiler": 0,
        "ThreadPoolServiceThread": 0,
        "CompositorTileWorker1": 0,
        "Chrome_ChildIOThread": 0,
        "CrGpuMain": 0,
        "VizCompositorThread": 0,
        "CrRendererMain": 0.0003,
        "Compositor": 0,
        "CompositorTileWorker3": 0,
        "CompositorTileWorker4": 0,
        "CompositorTileWorker2": 0,
        "CompositorTileWorkerBackground": 0,
        "": 0
    }, {
        "NetworkService": 0.0008,
        "ThreadPoolForegroundWorker": 0,
        "CrBrowserMain": 0.0003,
        "Chrome_DevToolsHandlerThread": 0.0001,
        "Chrome_IOThread": 0.0001,
        "CacheThread_BlockFile": 0.0003,
        "StackSamplingProfiler": 0,
        "CompositorTileWorker1": 0,
        "ThreadPoolServiceThread": 0,
        "Chrome_ChildIOThread": 0.0001,
        "CrGpuMain": 0,
        "VizCompositorThread": 0,
        "CrRendererMain": 0.0024,
        "Compositor": 0.0001,
        "CompositorTileWorker3": 0,
        "CompositorTileWorker4": 0,
        "CompositorTileWorker2": 0,
        "CompositorTileWorkerBackground": 0,
        "": 0
    }, {
        "ThreadPoolForegroundWorker": 0,
        "Chrome_ChildIOThread": 0,
        "CrGpuMain": 0,
        "VizCompositorThread": 0,
        "NetworkService": 0.0001,
        "CrBrowserMain": 0,
        "Chrome_DevToolsHandlerThread": 0,
        "Chrome_IOThread": 0,
        "CacheThread_BlockFile": 0.0001,
        "StackSamplingProfiler": 0,
        "CompositorTileWorker1": 0,
        "ThreadPoolServiceThread": 0,
        "ThreadPoolSingleThreadForegroundBlocking1": 0,
        "MemoryInfra": 0,
        "CrRendererMain": 0.0005,
        "Compositor": 0,
        "CompositorTileWorker4": 0,
        "CompositorTileWorker2": 0,
        "CompositorTileWorker3": 0,
        "CompositorTileWorkerBackground": 0,
        "": 0
    }, {
        "NetworkService": 0.0001,
        "CrBrowserMain": 0,
        "ThreadPoolForegroundWorker": 0,
        "Chrome_DevToolsHandlerThread": 0,
        "Chrome_IOThread": 0,
        "CacheThread_BlockFile": 0.0001,
        "StackSamplingProfiler": 0,
        "CompositorTileWorker1": 0,
        "ThreadPoolServiceThread": 0,
        "Chrome_ChildIOThread": 0,
        "CrGpuMain": 0,
        "VizCompositorThread": 0,
        "CrRendererMain": 0.0006,
        "Compositor": 0,
        "CompositorTileWorker4": 0,
        "CompositorTileWorker2": 0,
        "CompositorTileWorker3": 0,
        "CompositorTileWorkerBackground": 0,
        "": 0
    }, {
        "ThreadPoolForegroundWorker": 0.0001,
        "Chrome_ChildIOThread": 0,
        "CrGpuMain": 0.0001,
        "VizCompositorThread": 0.0002,
        "NetworkService": 0.0002,
        "CrBrowserMain": 0.0001,
        "Chrome_DevToolsHandlerThread": 0,
        "Chrome_IOThread": 0,
        "CacheThread_BlockFile": 0.0001,
        "StackSamplingProfiler": 0,
        "CompositorTileWorker1": 0,
        "ThreadPoolServiceThread": 0,
        "CrRendererMain": 0.0011,
        "Compositor": 0.0001,
        "CompositorTileWorker3": 0,
        "CompositorTileWorker2": 0,
        "CompositorTileWorker4": 0,
        "CompositorTileWorkerBackground": 0,
        "": 0
    }]
}